LICENSE
README.md
setup.cfg
setup.py
custom_airflow_plugins/__init__.py
custom_airflow_plugins.egg-info/PKG-INFO
custom_airflow_plugins.egg-info/SOURCES.txt
custom_airflow_plugins.egg-info/dependency_links.txt
custom_airflow_plugins.egg-info/requires.txt
custom_airflow_plugins.egg-info/top_level.txt
custom_airflow_plugins/hooks/__init__.py
custom_airflow_plugins/hooks/dremio_hook.py
custom_airflow_plugins/hooks/mssql_hook.py
custom_airflow_plugins/hooks/postgres_hook.py
custom_airflow_plugins/hooks/util/__init__.py
custom_airflow_plugins/hooks/util/s3.py
custom_airflow_plugins/operators/__init__.py
custom_airflow_plugins/operators/db_2_db_operator.py
custom_airflow_plugins/operators/db_2_s3_operator.py
custom_airflow_plugins/util/__init__.py
custom_airflow_plugins/util/convert_helpers.py
custom_airflow_plugins/util/mongo.py