Metadata-Version: 2.1
Name: custom-airflow-plugins
Version: 1.0.5
Summary: Custom airflow 2.X plugins
Home-page: UNKNOWN
Author: Victor Outtes
Author-email: victor.outtes@gmail.com
License: MIT
Keywords: airflow,plugins
Platform: UNKNOWN
Classifier: Development Status :: 5 - Production/Stable
Classifier: Intended Audience :: Developers
Classifier: Topic :: Software Development :: Build Tools
Classifier: License :: OSI Approved :: MIT License
Classifier: Programming Language :: Python :: 3.7
Classifier: Programming Language :: Python :: 3.8
Classifier: Programming Language :: Python :: 3.9
License-File: LICENSE
